WHIutils
