Metadata-Version: 1.1
Name: webheroes-utils
Version: 0.0.4
Summary: Set of python utils made specifically for Web Heroes Inc.
Home-page: https://github.com/webheroesinc/webheroes-utils
Author: Matthew Brisebois
Author-email: matthew@webheroes.ca
License: Dual License; GPLv3 and Proprietary
Platform: UNKNOWN
Classifier: License :: OSI Approved :: GNU General Public License v3 or later (GPLv3+)
Classifier: License :: Other/Proprietary License
Classifier: Programming Language :: Python :: 2.7
Classifier: Development Status :: 4 - Beta
Classifier: Intended Audience :: Developers
